gitlab_artifact_cleanup/__init__.py
gitlab_artifact_cleanup/_version.py
gitlab_artifact_cleanup/artifact_cleanup.py
gitlab_artifact_cleanup/cli.py
gitlab_artifact_cleanup/config.py
gitlab_artifact_cleanup/util.py
gitlab_artifact_cleanup-0.1.0.dist-info/LICENSE
gitlab_artifact_cleanup-0.1.0.dist-info/METADATA
gitlab_artifact_cleanup-0.1.0.dist-info/WHEEL
gitlab_artifact_cleanup-0.1.0.dist-info/entry_points.txt
gitlab_artifact_cleanup-0.1.0.dist-info/top_level.txt
gitlab_artifact_cleanup-0.1.0.dist-info/RECORD
