Metadata-Version: 2.2
Name: gitlab-artifact-cleanup
Version: 0.1.0
Summary: A tool for cleaning up gitlab artifacts
Author-email: Ingo Meyer <i.meyer@fz-juelich.de>
Maintainer-email: Ingo Meyer <i.meyer@fz-juelich.de>
License: Copyright 2025 Forschungszentrum Jülich GmbH
Project-URL: Homepage, https://github.com/sciapp/gitlab-artifact-cleanup
Keywords: gitlab,artifacts,cleanup
Classifier: Development Status :: 4 - Beta
Classifier: Environment :: Console
Classifier: Intended Audience :: Developers
Classifier: Intended Audience :: System Administrators
Classifier: License :: OSI Approved :: MIT License
Classifier: Natural Language :: English
Classifier: Operating System :: MacOS
Classifier: Operating System :: Microsoft :: Windows
Classifier: Operating System :: POSIX :: Linux
Classifier: Programming Language :: Python
Classifier: Programming Language :: Python :: 3
Classifier: Programming Language :: Python :: 3 :: Only
Classifier: Programming Language :: Python :: 3.9
Classifier: Programming Language :: Python :: 3.10
Classifier: Programming Language :: Python :: 3.11
Classifier: Programming Language :: Python :: 3.12
Classifier: Programming Language :: Python :: 3.13
Classifier: Programming Language :: Python :: 3.14
Classifier: Topic :: Utilities
Requires-Python: >=3.9
License-File: LICENSE
Requires-Dist: python-gitlab
Requires-Dist: yacl[colored_exceptions]
